{
    "boilerplate": {
        "/srv/boilerplate": true
    },
    "local_neutrino_control_app": {
        "/srv/boilerplate/neutrino-webapp-modules/local_neutrino_control_app": true
    },
    "background": {
        "/srv/boilerplate/vue-component-modules/background": true
    },
    "admin": {
        "/srv/boilerplate/@angularjs-modules/admin": false,
        "/srv/boilerplate/@server-modules/admin": false,
        "/srv/boilerplate/@vue-modules/admin": false
    },
    "angularjs": {
        "/srv/boilerplate/@angularjs-modules/angularjs": false,
        "/srv/boilerplate/@codepad-modules/angularjs": false
    },
    "frontend": {
        "/srv/boilerplate/@angularjs-modules/frontend": false
    },
    "frontendlib": {
        "/srv/boilerplate/@angularjs-modules/frontendlib": false
    },
    "language": {
        "/srv/boilerplate/@angularjs-modules/language": false
    },
    "passport": {
        "/srv/boilerplate/@angularjs-modules/passport": false,
        "/srv/boilerplate/@server-modules/passport": false
    },
    "profile": {
        "/srv/boilerplate/@angularjs-modules/profile": false
    },
    "promo": {
        "/srv/boilerplate/@angularjs-modules/promo": false
    },
    "session": {
        "/srv/boilerplate/@angularjs-modules/session": false,
        "/srv/boilerplate/@server-modules/session": false
    },
    "smartforms": {
        "/srv/boilerplate/@angularjs-modules/smartforms": false
    },
    "ansi": {
        "/srv/boilerplate/@codepad-modules/ansi": false
    },
    "basicauth": {
        "/srv/boilerplate/@codepad-modules/basicauth": false
    },
    "beautify": {
        "/srv/boilerplate/@codepad-modules/beautify": false
    },
    "codemirror": {
        "/srv/boilerplate/@codepad-modules/codemirror": false
    },
    "codepad": {
        "/srv/boilerplate/@codepad-modules/codepad": false
    },
    "defaults": {
        "/srv/boilerplate/@codepad-modules/defaults": false
    },
    "exec": {
        "/srv/boilerplate/@codepad-modules/exec": false
    },
    "favicon": {
        "/srv/boilerplate/@codepad-modules/favicon": false,
        "/srv/boilerplate/@server-modules/favicon": false
    },
    "filetree": {
        "/srv/boilerplate/@codepad-modules/filetree": false
    },
    "index": {
        "/srv/boilerplate/@codepad-modules/index": false
    },
    "lint": {
        "/srv/boilerplate/@codepad-modules/lint": false
    },
    "logs": {
        "/srv/boilerplate/@codepad-modules/logs": false
    },
    "main": {
        "/srv/boilerplate/@codepad-modules/main": false
    },
    "ot": {
        "/srv/boilerplate/@codepad-modules/ot": false
    },
    "pad": {
        "/srv/boilerplate/@codepad-modules/pad": false
    },
    "projectfiles": {
        "/srv/boilerplate/@codepad-modules/projectfiles": false
    },
    "pty": {
        "/srv/boilerplate/@codepad-modules/pty": false
    },
    "search": {
        "/srv/boilerplate/@codepad-modules/search": false
    },
    "server": {
        "/srv/boilerplate/@codepad-modules/server": false,
        "/srv/boilerplate/@server-modules/server": false
    },
    "socketio": {
        "/srv/boilerplate/@codepad-modules/socketio": false,
        "/srv/boilerplate/@server-modules/socketio": false,
        "/srv/boilerplate/@vue-modules/socketio": false
    },
    "wetty": {
        "/srv/boilerplate/@codepad-modules/wetty": false
    },
    "animate": {
        "/srv/boilerplate/@frontend-modules/animate": false
    },
    "bootstrap3": {
        "/srv/boilerplate/@frontend-modules/bootstrap3": false
    },
    "fontawesome4": {
        "/srv/boilerplate/@frontend-modules/fontawesome4": false
    },
    "jquery": {
        "/srv/boilerplate/@frontend-modules/jquery": false
    },
    "mobile_detect": {
        "/srv/boilerplate/@frontend-modules/mobile_detect": false
    },
    "mongo_express": {
        "/srv/boilerplate/@frontend-modules/mongo_express": false
    },
    "offline": {
        "/srv/boilerplate/@frontend-modules/offline": false
    },
    "vue-kit": {
        "/srv/boilerplate/@frontend-modules/vue-kit": false
    },
    "async": {
        "/srv/boilerplate/@javascript-modules/async": false
    },
    "devel_iframe": {
        "/srv/boilerplate/@javascript-modules/devel_iframe": false
    },
    "jest": {
        "/srv/boilerplate/@javascript-modules/jest": false
    },
    "mikrotik": {
        "/srv/boilerplate/@javascript-modules/mikrotik": false
    },
    "moment": {
        "/srv/boilerplate/@javascript-modules/moment": false
    },
    "xilica_neutrino": {
        "/srv/boilerplate/@javascript-modules/xilica_neutrino": false
    },
    "nativescript": {
        "/srv/boilerplate/@nativescript-modules/nativescript": false
    },
    "payment": {
        "/srv/boilerplate/@payment-modules/payment": false
    },
    "payment_barion": {
        "/srv/boilerplate/@payment-modules/payment_barion": false
    },
    "payment_braintree": {
        "/srv/boilerplate/@payment-modules/payment_braintree": false
    },
    "payment_simplepay": {
        "/srv/boilerplate/@payment-modules/payment_simplepay": false
    },
    "szamlazz": {
        "/srv/boilerplate/@payment-modules/szamlazz": false
    },
    "adminlogs": {
        "/srv/boilerplate/@server-modules/adminlogs": false
    },
    "api": {
        "/srv/boilerplate/@server-modules/api": false
    },
    "cors": {
        "/srv/boilerplate/@server-modules/cors": false
    },
    "logging": {
        "/srv/boilerplate/@server-modules/logging": false
    },
    "mongoose": {
        "/srv/boilerplate/@server-modules/mongoose": false
    },
    "multilanguage": {
        "/srv/boilerplate/@server-modules/multilanguage": false,
        "/srv/boilerplate/@vue-modules/multilanguage": false
    },
    "nodemailer": {
        "/srv/boilerplate/@server-modules/nodemailer": false
    },
    "passport_admin": {
        "/srv/boilerplate/@server-modules/passport_admin": false
    },
    "passport_facebook": {
        "/srv/boilerplate/@server-modules/passport_facebook": false
    },
    "passport_google": {
        "/srv/boilerplate/@server-modules/passport_google": false
    },
    "passport_hash": {
        "/srv/boilerplate/@server-modules/passport_hash": false
    },
    "readme": {
        "/srv/boilerplate/@server-modules/readme": false
    },
    "socketio-stream": {
        "/srv/boilerplate/@server-modules/socketio-stream": false
    },
    "verify": {
        "/srv/boilerplate/@server-modules/verify": false
    },
    "app": {
        "/srv/boilerplate/@vue-modules/app": false
    },
    "bootstrap-vue": {
        "/srv/boilerplate/@vue-modules/bootstrap-vue": false
    },
    "fontawesome5": {
        "/srv/boilerplate/@vue-modules/fontawesome5": false
    },
    "jsoneditor": {
        "/srv/boilerplate/@vue-modules/jsoneditor": false
    },
    "login": {
        "/srv/boilerplate/@vue-modules/login": false
    },
    "vue": {
        "/srv/boilerplate/@vue-modules/vue": false
    },
    "vuetify": {
        "/srv/boilerplate/@vue-modules/vuetify": false
    }
}